gradient_utils/__init__.py
gradient_utils/exceptions.py
gradient_utils/metrics/__init__.py
gradient_utils/metrics/env.py
gradient_utils/metrics/init.py
gradient_utils/metrics/metrics.py
gradient_utils/multi_node.py
gradient_utils/utils.py
gradient_utils-0.5.0.dist-info/WHEEL
gradient_utils-0.5.0.dist-info/METADATA
gradient_utils-0.5.0.dist-info/RECORD
