Metadata-Version: 2.1
Name: gradient-utils
Version: 0.5.0
Summary: This is an SDK for performing Machine Learning with Gradient.
Home-page: https://github.com/Paperspace/gradient-utils
License: MIT
Keywords: gradient,utils,sdk,ml
Author: Paperspace Co.
Author-email: info@paperspace.com
Requires-Python: >=3.6,<4.0
Classifier: Development Status :: 3 - Alpha
Classifier: Intended Audience :: Developers
Classifier: License :: OSI Approved :: MIT License
Classifier: Programming Language :: Python :: 3
Classifier: Programming Language :: Python :: 3.10
Classifier: Programming Language :: Python :: 3.6
Classifier: Programming Language :: Python :: 3.7
Classifier: Programming Language :: Python :: 3.8
Classifier: Programming Language :: Python :: 3.9
Classifier: Topic :: Software Development :: Libraries
Requires-Dist: prometheus-client (>=0.8,<0.10)
Requires-Dist: pymongo (>=3.11.0,<4.0.0)
Requires-Dist: wheel (>=0.35.1,<0.36.0)
Project-URL: Repository, https://github.com/Paperspace/gradient-utils
